cgspan_mining/__init__.py
cgspan_mining/__main__.py
cgspan_mining/cgspan.py
cgspan_mining/config.py
cgspan_mining/dfscode.py
cgspan_mining/graph.py
cgspan_mining/main.py
cgspan_mining/trie.py
cgspan_mining-1.0.1.dist-info/LICENSE
cgspan_mining-1.0.1.dist-info/METADATA
cgspan_mining-1.0.1.dist-info/WHEEL
cgspan_mining-1.0.1.dist-info/top_level.txt
cgspan_mining-1.0.1.dist-info/RECORD
