Metadata-Version: 2.1
Name: cgspan-mining
Version: 1.0.1
Summary: Implementation of close frequent subgraph mining algorithm cgSpan
Home-page: https://github.com/NaazS03/cgSpan
Author: Naazish Sheikh
Author-email: Naazish.Sheikh@gmail.com
License: UNKNOWN
Platform: UNKNOWN
Classifier: Programming Language :: Python :: 3
Classifier: License :: OSI Approved :: MIT License
Classifier: Operating System :: OS Independent
License-File: LICENSE
